multiclean/__init__.py
multiclean/__version__.py
multiclean/multiclean.py
multiclean/utils.py
multiclean-0.2.0.dist-info/licenses/LICENSE
multiclean-0.2.0.dist-info/METADATA
multiclean-0.2.0.dist-info/WHEEL
multiclean-0.2.0.dist-info/top_level.txt
multiclean-0.2.0.dist-info/RECORD
