Metadata-Version: 2.4
Name: multiclean
Version: 0.2.0
Summary: Python library for morphological cleaning of multiclass 2D numpy arrays (edge smoothing and island removal)
Author-email: Nick Wright <nicholas.wright@dpird.wa.gov.au>
License-Expression: MIT
Project-URL: Homepage, https://github.com/DPIRD-DMA/MultiClean
Keywords: morphological-operations,multiclass,classification-arrays,image-processing,edge-cleaning,island-removal,segmentation,post-processing,numpy,opencv,remote-sensing,computer-vision,noise-reduction
Requires-Python: >=3.9
License-File: LICENSE
Requires-Dist: opencv-python>=4.0
Requires-Dist: scipy>=1.0
Dynamic: license-file
